ndx_pose/spec/ndx-pose.extensions.yaml
ndx_pose/spec/ndx-pose.namespace.yaml
ndx_pose/__init__.py
ndx_pose/pose.py
ndx_pose/io/__init__.py
ndx_pose/io/pose.py
ndx_pose/testing/mock/__init__.py
ndx_pose/testing/mock/pose.py
ndx_pose-0.2.2.dist-info/METADATA
ndx_pose-0.2.2.dist-info/WHEEL
ndx_pose-0.2.2.dist-info/licenses/LICENSE.txt
ndx_pose-0.2.2.dist-info/RECORD
