Metadata-Version: 2.4
Name: ndx-pose
Version: 0.2.2
Summary: NWB extension to store pose estimation data
Project-URL: Homepage, https://github.com/rly/ndx-pose
Project-URL: Bug Tracker, https://github.com/rly/ndx-pose/issues
Project-URL: Changelog, https://github.com/rly/ndx-pose/blob/main/CHANGELOG.md
Author-email: Ryan Ly <rly@lbl.gov>, Ben Dichter <bdichter@lbl.gov>, Alexander Mathis <alexander.mathis@epfl.ch>, Liezl Maree <lmaree@salk.edu>, Chris Brozdowski <Chris.Broz@ucsf.edu>, Heberto Mayorquin <h.mayorquin@gmail.com>, Talmo Pereira <talmo@salk.edu>, Elizabeth Berrigan <eberrigan@salk.edu>
License: BSD-3
License-File: LICENSE.txt
Keywords: NWB,NeurodataWithoutBorders,ndx-extension,nwb-extension
Classifier: Development Status :: 4 - Beta
Classifier: Intended Audience :: Developers
Classifier: Intended Audience :: Science/Research
Classifier: License :: OSI Approved :: BSD License
Classifier: Programming Language :: Python
Classifier: Programming Language :: Python :: 3.8
Classifier: Programming Language :: Python :: 3.9
Classifier: Programming Language :: Python :: 3.10
Classifier: Programming Language :: Python :: 3.11
Classifier: Programming Language :: Python :: 3.12
Classifier: Programming Language :: Python :: 3.13
Requires-Python: >=3.8
Requires-Dist: hdmf>=3.13.0
Requires-Dist: pynwb>=2.6.0
Provides-Extra: dev
Requires-Dist: black>=24.4.2; extra == 'dev'
Requires-Dist: codespell>=2.3.0; extra == 'dev'
Requires-Dist: coverage>=7.5.4; extra == 'dev'
Requires-Dist: hdmf-docutils>=0.4.7; extra == 'dev'
Requires-Dist: pre-commit>=3.5.0; extra == 'dev'
Requires-Dist: pytest-cov>=5.0.0; extra == 'dev'
Requires-Dist: pytest-subtests>=0.12.1; extra == 'dev'
Requires-Dist: pytest>=8.2.2; extra == 'dev'
Requires-Dist: python-dateutil>=2.8.2; extra == 'dev'
Requires-Dist: ruff>=0.4.10; extra == 'dev'
Provides-Extra: docs
Requires-Dist: hdmf-docutils>=0.4.7; extra == 'docs'
Provides-Extra: min-reqs
Requires-Dist: hdmf==3.13.0; extra == 'min-reqs'
Requires-Dist: pynwb==2.6.0; extra == 'min-reqs'
Provides-Extra: test
Requires-Dist: coverage>=7.5.4; extra == 'test'
Requires-Dist: pytest-cov>=5.0.0; extra == 'test'
Requires-Dist: pytest-subtests>=0.12.1; extra == 'test'
Requires-Dist: pytest>=8.2.2; extra == 'test'
Requires-Dist: python-dateutil>=2.8.2; extra == 'test'
